{
  "products": [
    {
      "name": "CAMISETA AZUL",
      "category": "POLOS",
      "price": "20",
      "image": "https://res.cloudinary.com/ddgpmxprs/image/upload/v1698096158/117578482_1_nia0m7.jpg",
      "description": "MANGA LARGA",
      "stock": "25",
      "id": 20
    },
    {
      "name": "xxxx",
      "category": "poloa",
      "price": "6",
      "image": "https://res.cloudinary.com/ddgpmxprs/image/upload/v1698096158/117578482_1_nia0m7.jpg",
      "id": 24
    },
    {
      "name": "POLOS",
      "category": "Accessories",
      "price": "25.6",
      "image": "https://res.cloudinary.com/ddgpmxprs/image/upload/v1698096158/117578482_1_nia0m7.jpg",
      "description": "xxx",
      "stock": "5",
      "id": 25
    },
    {
      "name": "señora pomxxxxx",
      "category": "Clothing",
      "price": "25.6",
      "image": "https://res.cloudinary.com/ddgpmxprs/image/upload/v1698095895/camiseta-kappa-fc-metz-training-2023-2024-blue-lt-blue-0_fk9tpc.jpg",
      "description": "vvvv",
      "stock": "5",
      "id": 28
    },
    {
      "name": "Botellas Osos",
      "category": "Botellas",
      "price": "5",
      "image": "https://res.cloudinary.com/ddgpmxprs/image/upload/v1698096158/117578482_1_nia0m7.jpg",
      "description": "Botella de vidrio",
      "stock": "22",
      "id": 30
    },
    {
      "name": "Camiseta ",
      "category": "polos",
      "price": "25.6",
      "image": "https://res.cloudinary.com/ddgpmxprs/image/upload/v1698095895/camiseta-kappa-fc-metz-training-2023-2024-blue-lt-blue-0_fk9tpc.jpg",
      "description": "polos",
      "stock": "5",
      "id": 31
    },
    {
      "name": "Botellas",
      "category": "Accessories",
      "price": "25.6",
      "image": "https://res.cloudinary.com/ddgpmxprs/image/upload/v1698096158/117578482_1_nia0m7.jpg",
      "description": "holasasss",
      "stock": "25",
      "id": 32
    },
    {
      "name": "POLOS",
      "category": "Clothing",
      "price": "25.6",
      "image": "https://res.cloudinary.com/ddgpmxprs/image/upload/v1698095895/camiseta-kappa-fc-metz-training-2023-2024-blue-lt-blue-0_fk9tpc.jpg",
      "description": "talla L",
      "stock": "5",
      "id": 33
    },
    {
      "name": "Polo",
      "category": "Accessories",
      "price": "25.6",
      "image": "https://res.cloudinary.com/ddgpmxprs/image/upload/v1698095895/camiseta-kappa-fc-metz-training-2023-2024-blue-lt-blue-0_fk9tpc.jpg",
      "description": "talla Xl",
      "stock": "22",
      "id": 34
    },
    {
      "name_administrador": "",
      "category": "Clothing",
      "price": "25.6",
      "image": "https://res.cloudinary.com/ddgpmxprs/image/upload/v1698095895/camiseta-kappa-fc-metz-training-2023-2024-blue-lt-blue-0_fk9tpc.jpg",
      "description": "talla L",
      "stock": "22",
      "name": "POLOS",
      "id": 35
    },
    {
      "name_administrador": "",
      "category": "Accessories",
      "price": "36.6",
      "image": "https://res.cloudinary.com/ddgpmxprs/image/upload/v1698096158/117578482_1_nia0m7.jpg",
      "description": "rojo/ verde",
      "stock": "5",
      "name": "n",
      "id": 36,
      "x": "nn"
    },
    {
      "name_administrador": "",
      "category": "Clothing",
      "price": "12.9",
      "image": "https://res.cloudinary.com/ddgpmxprs/image/upload/v1698095895/camiseta-kappa-fc-metz-training-2023-2024-blue-lt-blue-0_fk9tpc.jpg",
      "description": "xs",
      "stock": "3",
      "name": "x",
      "id": 37,
      "x": "xx"
    },
    {
      "Name_product": "Polo sintetico",
      "category": "Clothing",
      "price": "20.3",
      "image": "https://res.cloudinary.com/ddgpmxprs/image/upload/v1698095895/camiseta-kappa-fc-metz-training-2023-2024-blue-lt-blue-0_fk9tpc.jpg",
      "description": "Talla Xs",
      "stock": "20",
      "id": 38,
      "x": "Rebeca Pomac"
    }
  ]
}